spinmc-0.1.2.dist-info/METADATA
spinmc-0.1.2.dist-info/WHEEL
spinmc-0.1.2.dist-info/entry_points.txt
spinmc.libs/libgcc_s-b5472b99.so.1
spinmc/__init__.py
spinmc/_spinmc.cpython-313t-i386-linux-musl.so
spinmc-0.1.2.dist-info/RECORD
