Metadata-Version: 2.4
Name: spinmc
Version: 0.1.2
Classifier: Programming Language :: Rust
Classifier: Programming Language :: Python :: Implementation :: CPython
Classifier: Programming Language :: Python :: Implementation :: PyPy
Requires-Dist: matplotlib>=3.1,<4.0
Requires-Dist: rtoml>=0.11.0
Requires-Dist: scipy>=1.2.0
Requires-Dist: typer>=0.16.0
Summary: spinmc
Requires-Python: >=3.9
